pycsi/Async/Subvalidator.py
pycsi/Async/Validator.py
pycsi/Async/__init__.py
pycsi/Sync/Subvalidator.py
pycsi/Sync/Validator.py
pycsi/Sync/__init__.py
pycsi/__init__.py
pycsi/utils/BaseSubValidator.py
pycsi/utils/BaseValidator.py
pycsi/utils/__init__.py
pycsi-0.1.0.dist-info/LICENSE
pycsi-0.1.0.dist-info/METADATA
pycsi-0.1.0.dist-info/WHEEL
pycsi-0.1.0.dist-info/RECORD
