Metadata-Version: 2.1
Name: pycsi
Version: 0.1.0
Summary: Simple Validation Library for Python
Home-page: https://github.com/EM51641/csi
License: MIT
Author: Elyes
Author-email: elyesmahjoubi@gmail.com
Requires-Python: >=3.10.12,<4.0.0
Classifier: License :: OSI Approved :: MIT License
Classifier: Operating System :: OS Independent
Classifier: Programming Language :: Python :: 3
Classifier: Programming Language :: Python :: 3.11
Classifier: Programming Language :: Python :: 3 :: Only
Classifier: Programming Language :: Python :: 3.10
Project-URL: Repository, https://github.com/EM51641/csi
